MANIFEST.in
README.md
setup.py
django_ecs_deploy.egg-info/PKG-INFO
django_ecs_deploy.egg-info/SOURCES.txt
django_ecs_deploy.egg-info/dependency_links.txt
django_ecs_deploy.egg-info/top_level.txt
ecs_deploy/__init__.py
ecs_deploy/management/__init__.py
ecs_deploy/management/commands/__init__.py
ecs_deploy/management/commands/ecsdeploy.py
ecs_deploy/templates/__init__.py
ecs_deploy/templates/dockerfile.tmpl
ecs_deploy/templates/ecstask.tmpl
ecs_deploy/templates/freetds.tmpl
ecs_deploy/templates/gunicorn.tmpl