Metadata-Version: 1.1
Name: django-ecs-deploy
Version: 0.1.14
Summary: A Django app that provides a command to deploy a Django app to AWS ECS based on Django settings.
Home-page: https://github.com/ethanmcc/django-ecs-deploy
Author: Ethan McCreadie
Author-email: ethanmcc@gmail.com
License: BSD License
Platform: UNKNOWN
Classifier: Environment :: Web Environment
Classifier: Framework :: Django
Classifier: Intended Audience :: Developers
Classifier: License :: OSI Approved :: BSD License
Classifier: Operating System :: OS Independent
Classifier: Programming Language :: Python
Classifier: Programming Language :: Python :: 3
Classifier: Programming Language :: Python :: 3.2
Classifier: Programming Language :: Python :: 3.3
Classifier: Topic :: Internet :: WWW/HTTP
Classifier: Topic :: Internet :: WWW/HTTP :: Dynamic Content
